SPyC_Writer/SPCDate.py
SPyC_Writer/SPCEnums.py
SPyC_Writer/SPCFileWriter.py
SPyC_Writer/SPCHeader.py
SPyC_Writer/SPCLog.py
SPyC_Writer/SPCSubheader.py
SPyC_Writer/__init__.py
SPyC_Writer/common.py
spyc_writer-1.0.1.dist-info/LICENSE
spyc_writer-1.0.1.dist-info/WHEEL
spyc_writer-1.0.1.dist-info/METADATA
spyc_writer-1.0.1.dist-info/RECORD
