Metadata-Version: 2.1
Name: SPyC_Writer
Version: 1.0.1
Summary: A program to output data in the Thermo Galactic SPC file format.
Author-email: Wasatch Photonics <sw-support@wasatchphotonics.com>
Classifier: License :: OSI Approved :: MIT License
Project-URL: Home, https://github.com/WasatchPhotonics/SPyC_Writer
